{"article":{"author_id":"96a8cc77-9928-440b-9254-34873bd8344f","content":"# Công thức Euler: Vẻ đẹp vĩnh cửu của Toán học\n\nTrong thế giới toán học, có một công thức được ví như một tác phẩm nghệ thuật kinh điển, kết hợp năm hằng số toán học quan trọng nhất vào một biểu thức duy nhất:\n\n$$e^{i\\pi} + 1 = 0$$\n\nCông thức này được phát minh bởi nhà toán học vĩ đại người Thụy Sĩ **Leonhard Euler**. Hãy cùng khám phá vì sao nó lại mang một vẻ đẹp kỳ diệu đến vậy.\n\n## Các thành phần cấu tạo\n\nBiểu thức này chứa đựng:\n* Hằng số $e$: Cơ số của logarit tự nhiên, xấp xỉ $2.71828$.\n* Đơn vị ảo $i$: Định nghĩa bởi $i^2 = -1$.\n* Hằng số $\\pi$: Tỉ số giữa chu vi và đường kính đường tròn, xấp xỉ $3.14159$.\n* Số $1$: Phần tử đơn vị của phép nhân.\n* Số $0$: Phần tử trung hòa của phép cộng.\n\n> [!TIP]\n> Sự liên kết của 5 đại lượng tưởng chừng như hoàn toàn khác biệt này thể hiện sự thống nhất sâu sắc của các phân môn toán học: Giải tích ($e$), Đại số ($i$), Hình học ($\\pi$), và Số học ($0, 1$).\n\n## Chứng minh toán học thông qua Chuỗi Taylor\n\nChúng ta có chuỗi lũy thừa Taylor của các hàm số lượng giác và hàm mũ:\n\n$$e^x = \\sum_{n=0}^{\\infty} \\frac{x^n}{n!} = 1 + x + \\frac{x^2}{2!} + \\frac{x^3}{3!} + \\dots$$\n\n$$\\cos x = 1 - \\frac{x^2}{2!} + \\frac{x^4}{4!} - \\dots$$\n\n$$\\sin x = x - \\frac{x^3}{3!} + \\frac{x^5}{5!} - \\dots$$\n\nThay $x = i\\theta$ vào chuỗi của $e^x$, ta thu được công thức tổng quát của Euler:\n\n$$e^{i\\theta} = \\cos\\theta + i\\sin\\theta$$\n\nKhi đặt $\\theta = \\pi$, ta có $\\cos\\pi = -1$ và $\\sin\\pi = 0$. Biểu thức trở thành:\n\n$$e^{i\\pi} = -1 + 0i \\implies e^{i\\pi} + 1 = 0$$\n\nĐây chính là vẻ đẹp bất tận mà bất kỳ ai học toán cũng đều say mê!","created_at":"2026-06-23T12:49:18","id":"a1111111-1111-1111-1111-111111111111","summary":"Khám phá công thức toán học đẹp nhất mọi thời đại e^(i*pi) + 1 = 0 của Leonhard Euler và ý nghĩa sâu sắc đằng sau nó.","title":"Công thức Euler và vẻ đẹp kỳ diệu của Toán học"},"success":true}